setup.cfg
setup.py
confload/__init__.py
confload/ini.py
confload/json.py
confload/yaml.py
nci_config_loader.egg-info/PKG-INFO
nci_config_loader.egg-info/SOURCES.txt
nci_config_loader.egg-info/dependency_links.txt
nci_config_loader.egg-info/requires.txt
nci_config_loader.egg-info/top_level.txt