Metadata-Version: 1.1
Name: nci-config-loader
Version: 1.0.12
Summary: Configuration file loader and parser
Home-page: https://github.com/newcraftgroup/nci-python-config
Author: Newcraft
Author-email: cedric.le.varlet@newcraftgroup.com
License: Apache License, Version 2.0
Download-URL: https://github.com/newcraftgroup/nci-python-config/tarball/master
Platform: UNKNOWN
Classifier: Development Status :: 4 - Beta
Classifier: Intended Audience :: Developers
Classifier: Operating System :: OS Independent
Classifier: Programming Language :: Python
Classifier: Programming Language :: Python :: 3
